python_ipware/__init__.py
python_ipware/__version__.py
python_ipware/py.typed
python_ipware/python_ipware.py
python_ipware-2.0.5.dist-info/LICENSE
python_ipware-2.0.5.dist-info/METADATA
python_ipware-2.0.5.dist-info/WHEEL
python_ipware-2.0.5.dist-info/top_level.txt
python_ipware-2.0.5.dist-info/RECORD
