Metadata-Version: 2.1
Name: python-ipware
Version: 2.0.5
Summary: A Python package to retrieve user's IP address
Author-email: Val Neekman <info@neekware.com>
License: MIT
Project-URL: Documentation, https://github.com/un33k/python-ipware#readme
Project-URL: Issues, https://github.com/un33k/python-ipware/issues
Project-URL: Source, https://github.com/un33k/python-ipware
Project-URL: Changelog, https://github.com/un33k/python-ipware/blob/main/CHANGELOG.md
Classifier: Development Status :: 4 - Beta
Classifier: Intended Audience :: Developers
Classifier: Natural Language :: English
Classifier: License :: OSI Approved :: MIT License
Classifier: Programming Language :: Python
Classifier: Programming Language :: Python :: 3
Classifier: Programming Language :: Python :: 3.7
Classifier: Programming Language :: Python :: 3.8
Classifier: Programming Language :: Python :: 3.9
Classifier: Programming Language :: Python :: 3.10
Classifier: Programming Language :: Python :: 3.11
Classifier: Programming Language :: Python :: 3.12
Requires-Python: >=3.7
License-File: LICENSE
Provides-Extra: dev
Requires-Dist: ruff ; extra == 'dev'
Requires-Dist: coveralls ~=3.3 ; extra == 'dev'
Requires-Dist: coverage[toml] ; extra == 'dev'
Requires-Dist: twine ; extra == 'dev'
